SerialScope/__init__.py
SerialScope/__main__.py
SerialScope/arduino.py
SerialScope/config.py
SerialScope/gui.py
SerialScope/helper.py
SerialScope/layout.py
SerialScope/scope.py
SerialScope-0.0.1.dist-info/LICENSE
SerialScope-0.0.1.dist-info/METADATA
SerialScope-0.0.1.dist-info/WHEEL
SerialScope-0.0.1.dist-info/entry_points.txt
SerialScope-0.0.1.dist-info/top_level.txt
SerialScope-0.0.1.dist-info/RECORD
