Metadata-Version: 2.1
Name: SerialScope
Version: 0.0.1
Summary: A serial-port based oscilloscope
Home-page: http://github.com/dilawar/SerialScope
Author: Dilawar Singh
Author-email: dilawars@ncbs.res.in
License: GPLv3
Platform: UNKNOWN
